trajan/__init__.py
trajan/accessor.py
trajan/animation/__init__.py
trajan/plot/__init__.py
trajan/plot/land.py
trajan/ragged.py
trajan/readers/__init__.py
trajan/readers/omb.py
trajan/readers/omb_decoder.py
trajan/scripts/trajaninfo.py
trajan/scripts/trajanshow.py
trajan/skill/__init__.py
trajan/traj.py
trajan/traj1d.py
trajan/traj2d.py
trajan/waves/__init__.py
trajan/waves/plot.py
trajan-0.8.0.dist-info/LICENSE
trajan-0.8.0.dist-info/METADATA
trajan-0.8.0.dist-info/WHEEL
trajan-0.8.0.dist-info/entry_points.txt
trajan-0.8.0.dist-info/RECORD
