Metadata-Version: 2.3
Name: trajan
Version: 0.8.0
Summary: Trajectory analysis package for simulated and observed trajectories
License: GPLv2
Author: Gaute Hope
Author-email: gauteh@met.no
Requires-Python: >=3.8,<4.0
Classifier: License :: Other/Proprietary License
Classifier: Programming Language :: Python :: 3
Classifier: Programming Language :: Python :: 3.8
Classifier: Programming Language :: Python :: 3.9
Classifier: Programming Language :: Python :: 3.10
Classifier: Programming Language :: Python :: 3.11
Classifier: Programming Language :: Python :: 3.12
Classifier: Programming Language :: Python :: 3.13
Requires-Dist: cartopy (>=0.21)
Requires-Dist: cf_xarray (>=0.8.0)
Requires-Dist: click (>=8.1.3,<9.0.0)
Requires-Dist: matplotlib (>=3.5)
Requires-Dist: netCDF4 (>=1.6)
Requires-Dist: numpy (>=1.23)
Requires-Dist: pandas (>=2)
Requires-Dist: pyproj (>=2.3)
Requires-Dist: scipy (>=1.9)
Requires-Dist: xarray (>=2022.6.0)
